{
  "user": [
    {
      "id": "c725",
      "username": "Rashmi",
      "email": "r@gmail.com",
      "password": "R@12345"
    },
    {
      "id": "5856",
      "username": "Rashmi",
      "email": "r@gmail.com",
      "password": "RRRRR"
    },
    {
      "id": "487c",
      "username": "Rashmi",
      "email": "r@gmail.com",
      "password": "rrrrr"
    },
    {
      "id": "d145",
      "username": "Nisha",
      "email": "n12@gmail.com",
      "password": "Node@12345"
    },
    {
      "id": "5201",
      "username": "Rashmi",
      "email": "admin@gmail.com",
      "password": "admin@123"
    },
    {
      "id": "85cf",
      "username": "Rashmi",
      "email": "node@gmail.com",
      "password": "R@12345"
    },
    {
      "id": "dbbf",
      "username": "Rashmi",
      "email": "node@gmail.com",
      "password": "FFFFFF"
    },
    {
      "id": "f740",
      "username": "Node",
      "email": "node@gmail.com",
      "password": "node"
    }
  ],
  "products": []
}
